poolcli/__init__.py
poolcli/exceptions.py
poolcli/main.py
poolcli/cli/__init__.py
poolcli/cli/auth.py
poolcli/cli/key.py
poolcli/cli/pool.py
poolcli/cli/refund.py
poolcli/cli/support.py
poolcli/cli/wallet.py
poolcli/core/__init__.py
poolcli/core/auth.py
poolcli/core/config.py
poolcli/core/constants.py
poolcli/core/key_manager.py
poolcli/core/pool_manager.py
poolcli/core/refund_manager.py
poolcli/core/wallet_manager.py
poolcli/utils/__init__.py
poolcli/utils/api_client.py
poolcli/utils/bittensor_utils.py
poolcli/utils/console.py
poolcli/utils/create_signature.py
poolcli/utils/error_handler.py
poolcli/utils/help.py
poolcli/utils/misc.py
poolcli-1.1.0.dist-info/METADATA
poolcli-1.1.0.dist-info/WHEEL
poolcli-1.1.0.dist-info/entry_points.txt
poolcli-1.1.0.dist-info/licenses/LICENSE
poolcli-1.1.0.dist-info/RECORD
