Metadata-Version: 2.4
Name: poolcli
Version: 1.1.0
Summary: A professional CLI for managing Bittensor subnet pool operations
Author-email: PoolCLI Team <admin@taopoolmining.com>
License-File: LICENSE
Keywords: bittensor,blockchain,cli,cryptocurrency,pool
Classifier: Development Status :: 3 - Alpha
Classifier: Intended Audience :: Developers
Classifier: License :: OSI Approved :: MIT License
Classifier: Programming Language :: Python :: 3
Classifier: Programming Language :: Python :: 3.10
Classifier: Programming Language :: Python :: 3.11
Classifier: Programming Language :: Python :: 3.12
Classifier: Topic :: System :: Systems Administration
Classifier: Topic :: Utilities
Requires-Python: >=3.10
Requires-Dist: async-substrate-interface>=1.5.6
Requires-Dist: bittensor>=9.12.0
Requires-Dist: click>=8.3.0
Requires-Dist: prompt-toolkit>=3.0.52
Requires-Dist: pydantic-settings>=2.11.0
Requires-Dist: requests>=2.28.0
Requires-Dist: rich>=14.2.0
Requires-Dist: substrate-interface>=1.7.0
Requires-Dist: wcwidth>=0.2.14
